NFW/__init__.py
NFW/mass_concentration.py
NFW/nfw.py
NFW-0.3.1.dist-info/LICENSE.txt
NFW-0.3.1.dist-info/METADATA
NFW-0.3.1.dist-info/WHEEL
NFW-0.3.1.dist-info/top_level.txt
NFW-0.3.1.dist-info/RECORD
