Metadata-Version: 2.1
Name: NFW
Version: 0.3.1
Summary: Python routines for computing Navarro-Frenk-White halo properties
Home-page: https://github.com/joergdietrich/NFW
Author: Jörg Dietrich
Author-email: astro@joergdietrich.com
License: MIT
Keywords: nfw halo astrophysics astronomy galaxy-clusters galaxies navarro-frenk-white
Classifier: Development Status :: 5 - Production/Stable
Classifier: Intended Audience :: Science/Research
Classifier: Topic :: Scientific/Engineering :: Astronomy
Classifier: License :: OSI Approved :: MIT License
Classifier: Programming Language :: Python :: 3
License-File: LICENSE.txt
Requires-Dist: numpy (>=1.9)
Requires-Dist: scipy (>=0.16)
Requires-Dist: astropy (>=2.0)
Provides-Extra: dev
Requires-Dist: pytest ; extra == 'dev'
Requires-Dist: pytest-cov ; extra == 'dev'
